objectmapper/__init__.py
objectmapper/__version__.py
objectmapper/exceptions.py
objectmapper/objectmapper.py
objectmapper-0.0.7.dist-info/LICENSE
objectmapper-0.0.7.dist-info/METADATA
objectmapper-0.0.7.dist-info/WHEEL
objectmapper-0.0.7.dist-info/top_level.txt
objectmapper-0.0.7.dist-info/RECORD
